unionfind/__init__.py
unionfind/py.typed
unionfind-0.2.1.dist-info/LICENSE
unionfind-0.2.1.dist-info/METADATA
unionfind-0.2.1.dist-info/WHEEL
unionfind-0.2.1.dist-info/RECORD
