Metadata-Version: 2.1
Name: unionfind
Version: 0.2.1
Summary: `unionfind` is a package for unionfind.
Home-page: https://github.com/SaitoTsutomu/unionfind
License: Apache-2.0
Author: SaitoTsutomu
Author-email: tsutomu7@hotmail.co.jp
Requires-Python: >=3.12,<4.0
Classifier: Development Status :: 1 - Planning
Classifier: License :: OSI Approved :: Apache Software License
Classifier: Programming Language :: Python
Classifier: Programming Language :: Python :: 3
Classifier: Programming Language :: Python :: 3.12
Classifier: Topic :: Scientific/Engineering
Classifier: Topic :: Software Development
